simplemathcaptcha/__init__.py
simplemathcaptcha/fields.py
simplemathcaptcha/utils.py
simplemathcaptcha/widgets.py
simplemathcaptcha/locale/es/LC_MESSAGES/django.mo
simplemathcaptcha/locale/es/LC_MESSAGES/django.po
simplemathcaptcha/locale/fr/LC_MESSAGES/django.mo
simplemathcaptcha/locale/fr/LC_MESSAGES/django.po
simplemathcaptcha/templates/simplemathcaptcha/captcha.html
test_simplemathcaptcha/__init__.py
test_simplemathcaptcha/field_tests.py
test_simplemathcaptcha/form_tests.py
test_simplemathcaptcha/models.py
test_simplemathcaptcha/tests.py
test_simplemathcaptcha/utils_tests.py
test_simplemathcaptcha/widget_tests.py
django_simple_math_captcha-2.0.dist-info/AUTHORS
django_simple_math_captcha-2.0.dist-info/METADATA
django_simple_math_captcha-2.0.dist-info/WHEEL
django_simple_math_captcha-2.0.dist-info/top_level.txt
django_simple_math_captcha-2.0.dist-info/RECORD
