Metadata-Version: 2.1
Name: django-simple-math-captcha
Version: 2.0
Summary: An easy-to-use math field/widget captcha for Django forms.
Home-page: https://alsoicode.github.io/
Author: Brandon Taylor
Author-email: alsoicode@gmail.com
License: UNKNOWN
Platform: UNKNOWN
Classifier: Development Status :: 5 - Production/Stable
Classifier: Environment :: Web Environment
Classifier: Framework :: Django
Classifier: Intended Audience :: Developers
Classifier: License :: OSI Approved :: Apache Software License
Classifier: Operating System :: OS Independent
Classifier: Programming Language :: Python
Classifier: Programming Language :: Python :: 2.7
Classifier: Programming Language :: Python :: 3
Classifier: Programming Language :: Python :: Implementation :: CPython
Classifier: Topic :: Utilities
